iottalkpy/__init__.py
iottalkpy/color.py
iottalkpy/dai.py
iottalkpy/dan.py
iottalkpy/exceptions.py
iottalkpy/utils.py
iottalk_py-2.3.1.dist-info/LICENSE
iottalk_py-2.3.1.dist-info/METADATA
iottalk_py-2.3.1.dist-info/WHEEL
iottalk_py-2.3.1.dist-info/top_level.txt
iottalk_py-2.3.1.dist-info/RECORD
