Metadata-Version: 2.1
Name: iottalk-py
Version: 2.3.1
Summary: UNKNOWN
Home-page: https://github.com/IoTtalk/iottalk-py
Author: the IoTtalk team
Author-email: iblis@hs.ntnu.edu.tw
Maintainer: Iblis Lin
Maintainer-email: iblis@hs.ntnu.edu.tw
License: UNKNOWN
Platform: Linux
Platform: FreeBSD
Classifier: Development Status :: 3 - Alpha
Classifier: Programming Language :: Python :: 2.7
Classifier: Programming Language :: Python :: 3.4
Classifier: Programming Language :: Python :: 3.5
Classifier: Programming Language :: Python :: 3.6
Classifier: Programming Language :: Python :: 3.7
Classifier: Programming Language :: Python :: Implementation :: CPython
Requires-Dist: iottalk-paho-mqtt (==1.4.0.dev3)
Requires-Dist: requests (>=2.22.0)
